console_access/console_access/console_access.py
console_access/console_access/console_access.rego
console_access/console_access/manifest.toml
console_access/console_access/test_console_access.py
mfa_enabled/mfa_enabled/manifest.toml
mfa_enabled/mfa_enabled/mfa_enabled.py
mfa_enabled/mfa_enabled/mfa_enabled.rego
mfa_enabled/mfa_enabled/test_mfa_enabled.py
overdue_api_keys/overdue_api_keys/manifest.toml
overdue_api_keys/overdue_api_keys/overdue_api_keys.py
overdue_api_keys/overdue_api_keys/overdue_api_keys.rego
overdue_api_keys/overdue_api_keys/test_overdue_api_keys.py
unused_policies/unused_policies/manifest.toml
unused_policies/unused_policies/test_unused_policies.py
unused_policies/unused_policies/unused_policies.py
unused_policies/unused_policies/unused_policies.rego
opsbox_aws_iam_checks-0.2.0.dist-info/LICENCE.txt
opsbox_aws_iam_checks-0.2.0.dist-info/METADATA
opsbox_aws_iam_checks-0.2.0.dist-info/WHEEL
opsbox_aws_iam_checks-0.2.0.dist-info/entry_points.txt
opsbox_aws_iam_checks-0.2.0.dist-info/top_level.txt
opsbox_aws_iam_checks-0.2.0.dist-info/RECORD
