Metadata-Version: 2.2
Name: opsbox-aws-iam-checks
Version: 0.2.0
Summary: Collection of IAM checks for opsbox
Requires-Python: ==3.11.*
License-File: LICENCE.txt
Requires-Dist: opsbox-iam-provider>=0.1.3
Requires-Dist: opsbox-rego-handler>=0.2.0
